Metadata-Version: 2.1
Name: takinai
Version: 0.0.1
Summary: The official Python library for the TakinAI API
Home-page: https://github.com/datamonet/takinai-python
Author: DataMonet LLC
Author-email: support@takin.ai
License: MIT
Classifier: License :: OSI Approved :: Apache Software License
Classifier: Programming Language :: Python
Classifier: Programming Language :: Python :: 3
License-File: LICENSE
